simulateur_trafic/__init__.py
simulateur_trafic/core/__init__.py
simulateur_trafic/core/analyseur.py
simulateur_trafic/core/exceptions.py
simulateur_trafic/core/simulateur.py
simulateur_trafic/data/config_reseau.json
simulateur_trafic/io/__init__.py
simulateur_trafic/io/affichage.py
simulateur_trafic/io/export.py
simulateur_trafic/models/__init__.py
simulateur_trafic/models/reseau.py
simulateur_trafic/models/route.py
simulateur_trafic/models/vehicule.py
simulateur_trafic_ysf-1.0.0.dist-info/METADATA
simulateur_trafic_ysf-1.0.0.dist-info/WHEEL
simulateur_trafic_ysf-1.0.0.dist-info/top_level.txt
simulateur_trafic_ysf-1.0.0.dist-info/RECORD
