Metadata-Version: 2.4
Name: simulateur-trafic-ysf
Version: 1.0.0
Summary: Un simulateur modulaire pour modéliser et analyser le trafic routier
Author-email: Your Name <your.email@example.com>
License-Expression: MIT
Project-URL: Homepage, https://github.com/yourusername/simulateur_trafic
Project-URL: Documentation, https://github.com/yourusername/simulateur_trafic#readme
Project-URL: Repository, https://github.com/yourusername/simulateur_trafic
Project-URL: Issues, https://github.com/yourusername/simulateur_trafic/issues
Keywords: traffic,simulation,routing,traffic-analysis
Classifier: Development Status :: 4 - Beta
Classifier: Intended Audience :: Developers
Classifier: Intended Audience :: Science/Research
Classifier: Programming Language :: Python :: 3
Classifier: Programming Language :: Python :: 3.9
Classifier: Programming Language :: Python :: 3.10
Classifier: Programming Language :: Python :: 3.11
Classifier: Programming Language :: Python :: 3.12
Classifier: Topic :: Scientific/Engineering
Classifier: Topic :: Software Development :: Libraries :: Python Modules
Requires-Python: >=3.9
Requires-Dist: matplotlib>=3.5.0
Requires-Dist: numpy>=1.21.0
Provides-Extra: dev
Requires-Dist: pytest>=7.0.0; extra == "dev"
Requires-Dist: pytest-cov>=4.0.0; extra == "dev"
Requires-Dist: flake8>=7.0.0; extra == "dev"
